<?xml version="1.0" encoding="utf-8"?>
<TextureAtlas imagePath="ducky_assets.png">
	<!-- Created with Adobe Animate version 21.0.5.40714 -->
	<!-- http://www.adobe.com/products/animate.html -->
	<SubTexture name="Idle0000" x="0" y="0" width="763" height="600" frameX="-7" frameY="-21" frameWidth="787" frameHeight="624"/>
	<SubTexture name="Idle0001" x="763" y="0" width="762" height="590" frameX="-12" frameY="-22" frameWidth="787" frameHeight="624"/>
	<SubTexture name="Idle0002" x="1525" y="0" width="756" height="618" frameX="-10" frameY="-6" frameWidth="787" frameHeight="624"/>
	<SubTexture name="Idle0003" x="2281" y="0" width="768" height="584" frameX="-7" frameY="-30" frameWidth="787" frameHeight="624"/>
	<SubTexture name="Idle0004" x="3049" y="0" width="764" height="589" frameX="0" frameY="-27" frameWidth="787" frameHeight="624"/>
	<SubTexture name="Idle0005" x="3813" y="0" width="768" height="608" frameX="-7" frameY="-13" frameWidth="787" frameHeight="624"/>
	<SubTexture name="Idle0006" x="4581" y="0" width="755" height="599" frameX="-12" frameY="-13" frameWidth="787" frameHeight="624"/>
	<SubTexture name="Idle0007" x="5336" y="0" width="774" height="624" frameX="-10" frameY="0" frameWidth="787" frameHeight="624"/>
	<SubTexture name="Idle0008" x="6110" y="0" width="780" height="593" frameX="-7" frameY="-21" frameWidth="787" frameHeight="624"/>
	<SubTexture name="Idle0009" x="6890" y="0" width="769" height="594" frameX="0" frameY="-22" frameWidth="787" frameHeight="624"/>
	<SubTexture name="down0000" x="0" y="624" width="698" height="482" frameX="0" frameY="-15" frameWidth="703" frameHeight="497"/>
	<SubTexture name="down0001" x="698" y="624" width="700" height="483" frameX="0" frameY="-14" frameWidth="703" frameHeight="497"/>
	<SubTexture name="down0002" x="1398" y="624" width="703" height="491" frameX="0" frameY="-6" frameWidth="703" frameHeight="497"/>
	<SubTexture name="down0003" x="2101" y="624" width="696" height="476" frameX="0" frameY="-21" frameWidth="703" frameHeight="497"/>
	<SubTexture name="down0004" x="2797" y="624" width="691" height="470" frameX="0" frameY="-27" frameWidth="703" frameHeight="497"/>
	<SubTexture name="down0005" x="3488" y="624" width="698" height="485" frameX="0" frameY="-12" frameWidth="703" frameHeight="497"/>
	<SubTexture name="down0006" x="4186" y="624" width="700" height="486" frameX="0" frameY="-11" frameWidth="703" frameHeight="497"/>
	<SubTexture name="down0007" x="4886" y="624" width="703" height="497"/>
	<SubTexture name="down0008" x="5589" y="624" width="696" height="482" frameX="0" frameY="-15" frameWidth="703" frameHeight="497"/>
	<SubTexture name="down0009" x="6285" y="624" width="691" height="483" frameX="0" frameY="-14" frameWidth="703" frameHeight="497"/>
	<SubTexture name="left0000" x="6976" y="624" width="660" height="515" frameX="-20" frameY="-14" frameWidth="684" frameHeight="529"/>
	<SubTexture name="left0001" x="0" y="1139" width="658" height="516" frameX="-23" frameY="-13" frameWidth="684" frameHeight="529"/>
	<SubTexture name="left0002" x="658" y="1139" width="684" height="523" frameX="0" frameY="-6" frameWidth="684" frameHeight="529"/>
	<SubTexture name="left0003" x="1342" y="1139" width="651" height="509" frameX="-27" frameY="-20" frameWidth="684" frameHeight="529"/>
	<SubTexture name="left0004" x="1993" y="1139" width="672" height="503" frameX="-1" frameY="-26" frameWidth="684" frameHeight="529"/>
	<SubTexture name="left0005" x="2665" y="1139" width="675" height="518" frameX="-5" frameY="-11" frameWidth="684" frameHeight="529"/>
	<SubTexture name="left0006" x="3340" y="1139" width="674" height="519" frameX="-7" frameY="-10" frameWidth="684" frameHeight="529"/>
	<SubTexture name="left0007" x="4014" y="1139" width="683" height="529" frameX="-1" frameY="0" frameWidth="684" frameHeight="529"/>
	<SubTexture name="left0008" x="4697" y="1139" width="658" height="515" frameX="-20" frameY="-14" frameWidth="684" frameHeight="529"/>
	<SubTexture name="left0009" x="5355" y="1139" width="650" height="516" frameX="-23" frameY="-13" frameWidth="684" frameHeight="529"/>
	<SubTexture name="right0000" x="6005" y="1139" width="743" height="619" frameX="-11" frameY="-4" frameWidth="774" frameHeight="623"/>
	<SubTexture name="right0001" x="6748" y="1139" width="771" height="614" frameX="0" frameY="-9" frameWidth="774" frameHeight="623"/>
	<SubTexture name="right0002" x="0" y="1758" width="751" height="623" frameX="-11" frameY="0" frameWidth="774" frameHeight="623"/>
	<SubTexture name="right0003" x="751" y="1758" width="769" height="615" frameX="-5" frameY="-8" frameWidth="774" frameHeight="623"/>
	<SubTexture name="right0004" x="1520" y="1758" width="746" height="614" frameX="-14" frameY="-9" frameWidth="774" frameHeight="623"/>
	<SubTexture name="right0005" x="2266" y="1758" width="738" height="619" frameX="-11" frameY="-4" frameWidth="774" frameHeight="623"/>
	<SubTexture name="right0006" x="3004" y="1758" width="769" height="614" frameX="0" frameY="-9" frameWidth="774" frameHeight="623"/>
	<SubTexture name="right0007" x="3773" y="1758" width="736" height="623" frameX="-11" frameY="0" frameWidth="774" frameHeight="623"/>
	<SubTexture name="right0008" x="4509" y="1758" width="749" height="615" frameX="-5" frameY="-8" frameWidth="774" frameHeight="623"/>
	<SubTexture name="right0009" x="5258" y="1758" width="757" height="614" frameX="-14" frameY="-9" frameWidth="774" frameHeight="623"/>
	<SubTexture name="up0000" x="6015" y="1758" width="671" height="610" frameX="-16" frameY="-5" frameWidth="693" frameHeight="615"/>
	<SubTexture name="up0001" x="6686" y="1758" width="692" height="607" frameX="0" frameY="-8" frameWidth="693" frameHeight="615"/>
	<SubTexture name="up0002" x="7378" y="1758" width="675" height="615" frameX="-18" frameY="0" frameWidth="693" frameHeight="615"/>
	<SubTexture name="up0003" x="0" y="2381" width="686" height="605" frameX="-6" frameY="-10" frameWidth="693" frameHeight="615"/>
	<SubTexture name="up0004" x="686" y="2381" width="659" height="603" frameX="-15" frameY="-12" frameWidth="693" frameHeight="615"/>
	<SubTexture name="up0005" x="1345" y="2381" width="671" height="610" frameX="-16" frameY="-5" frameWidth="693" frameHeight="615"/>
	<SubTexture name="up0006" x="2016" y="2381" width="692" height="607" frameX="0" frameY="-8" frameWidth="693" frameHeight="615"/>
	<SubTexture name="up0007" x="2708" y="2381" width="675" height="615" frameX="-18" frameY="0" frameWidth="693" frameHeight="615"/>
	<SubTexture name="up0008" x="3383" y="2381" width="686" height="605" frameX="-6" frameY="-10" frameWidth="693" frameHeight="615"/>
	<SubTexture name="up0009" x="4069" y="2381" width="659" height="603" frameX="-15" frameY="-12" frameWidth="693" frameHeight="615"/>
</TextureAtlas>
